odoo10_addon_delivery_multi_destination-10.0.1.0.0-py2.7-nspkg.pth
odoo/addons/delivery_multi_destination/README.rst
odoo/addons/delivery_multi_destination/__init__.py
odoo/addons/delivery_multi_destination/__manifest__.py
odoo/addons/delivery_multi_destination/i18n/es.po
odoo/addons/delivery_multi_destination/models/__init__.py
odoo/addons/delivery_multi_destination/models/delivery_carrier.py
odoo/addons/delivery_multi_destination/static/description/icon.png
odoo/addons/delivery_multi_destination/tests/__init__.py
odoo/addons/delivery_multi_destination/tests/test_delivery_multi_destination.py
odoo/addons/delivery_multi_destination/views/delivery_carrier_view.xml
odoo10_addon_delivery_multi_destination-10.0.1.0.0.dist-info/DESCRIPTION.rst
odoo10_addon_delivery_multi_destination-10.0.1.0.0.dist-info/METADATA
odoo10_addon_delivery_multi_destination-10.0.1.0.0.dist-info/RECORD
odoo10_addon_delivery_multi_destination-10.0.1.0.0.dist-info/WHEEL
odoo10_addon_delivery_multi_destination-10.0.1.0.0.dist-info/metadata.json
odoo10_addon_delivery_multi_destination-10.0.1.0.0.dist-info/namespace_packages.txt
odoo10_addon_delivery_multi_destination-10.0.1.0.0.dist-info/top_level.txt
